oauthlib-stubs/METADATA.toml
oauthlib-stubs/__init__.pyi
oauthlib-stubs/common.pyi
oauthlib-stubs/py.typed
oauthlib-stubs/signals.pyi
oauthlib-stubs/uri_validate.pyi
oauthlib-stubs/oauth1/__init__.pyi
oauthlib-stubs/oauth1/rfc5849/__init__.pyi
oauthlib-stubs/oauth1/rfc5849/errors.pyi
oauthlib-stubs/oauth1/rfc5849/parameters.pyi
oauthlib-stubs/oauth1/rfc5849/request_validator.pyi
oauthlib-stubs/oauth1/rfc5849/signature.pyi
oauthlib-stubs/oauth1/rfc5849/utils.pyi
oauthlib-stubs/oauth1/rfc5849/endpoints/__init__.pyi
oauthlib-stubs/oauth1/rfc5849/endpoints/access_token.pyi
oauthlib-stubs/oauth1/rfc5849/endpoints/authorization.pyi
oauthlib-stubs/oauth1/rfc5849/endpoints/base.pyi
oauthlib-stubs/oauth1/rfc5849/endpoints/pre_configured.pyi
oauthlib-stubs/oauth1/rfc5849/endpoints/request_token.pyi
oauthlib-stubs/oauth1/rfc5849/endpoints/resource.pyi
oauthlib-stubs/oauth1/rfc5849/endpoints/signature_only.pyi
oauthlib-stubs/oauth2/__init__.pyi
oauthlib-stubs/oauth2/rfc6749/__init__.pyi
oauthlib-stubs/oauth2/rfc6749/errors.pyi
oauthlib-stubs/oauth2/rfc6749/parameters.pyi
oauthlib-stubs/oauth2/rfc6749/request_validator.pyi
oauthlib-stubs/oauth2/rfc6749/tokens.pyi
oauthlib-stubs/oauth2/rfc6749/utils.pyi
oauthlib-stubs/oauth2/rfc6749/clients/__init__.pyi
oauthlib-stubs/oauth2/rfc6749/clients/backend_application.pyi
oauthlib-stubs/oauth2/rfc6749/clients/base.pyi
oauthlib-stubs/oauth2/rfc6749/clients/legacy_application.pyi
oauthlib-stubs/oauth2/rfc6749/clients/mobile_application.pyi
oauthlib-stubs/oauth2/rfc6749/clients/service_application.pyi
oauthlib-stubs/oauth2/rfc6749/clients/web_application.pyi
oauthlib-stubs/oauth2/rfc6749/endpoints/__init__.pyi
oauthlib-stubs/oauth2/rfc6749/endpoints/authorization.pyi
oauthlib-stubs/oauth2/rfc6749/endpoints/base.pyi
oauthlib-stubs/oauth2/rfc6749/endpoints/introspect.pyi
oauthlib-stubs/oauth2/rfc6749/endpoints/metadata.pyi
oauthlib-stubs/oauth2/rfc6749/endpoints/pre_configured.pyi
oauthlib-stubs/oauth2/rfc6749/endpoints/resource.pyi
types_oauthlib-3.3.0.20250814.dist-info/licenses/LICENSE
types_oauthlib-3.3.0.20250814.dist-info/METADATA
types_oauthlib-3.3.0.20250814.dist-info/WHEEL
types_oauthlib-3.3.0.20250814.dist-info/top_level.txt
types_oauthlib-3.3.0.20250814.dist-info/RECORD
